Workbook

Sheet Inputs
A1: Assumption | B1: Value
A2: Last historical revenue | B2: 1200
A3: Revenue growth | B3: 0.05
A4: EBIT margin | B4: 0.12
A5: Tax rate | B5: 0.25
A6: D&A % revenue | B6: 0.04
A7: Capex % revenue | B7: 0.05
A8: NWC % revenue | B8: 0.1
A9: Risk-free rate | B9: 0.028
A10: Equity risk premium | B10: 0.055
A11: Beta | B11: 1.1
A12: Pre-tax cost of debt | B12: 0.045
A13: Debt weight D/(D+E) | B13: 0.3
... A16: Shares outstanding | B16: 80
A18: Cost of equity (CAPM) | B18: =Inputs!$B$9+Inputs!$B$11*Inputs!$B$10
A19: WACC | B19: =(1-Inputs!$B$13)*Inputs!$B$18+Inputs!$B$13*Inputs!$B$12*(1-Inputs!$B$5)

Sheet Model
A1: Year | B1: 0 | C1: 1 | D1: 2 | E1: 3 | F1: 4 | G1: 5
A2: Revenue | B2: =Inputs!$B$2 | C2: =B2*(1+Inputs!$B$3) | D2: =C2*(1+Inputs!$B$3) | E2: =D2*(1+Inputs!$B$3) | F2: =E2*(1+Inputs!$B$3) | G2: =F2*(1+Inputs!$B$3)
A3: EBIT | C3: =C2*Inputs!$B$4 | D3: =D2*Inputs!$B$4 | E3: =E2*Inputs!$B$4 | F3: =F2*Inputs!$B$4 | G3: =G2*Inputs!$B$4
A4: NOPAT | C4: =C3*(1-Inputs!$B$5) | D4: =D3*(1-Inputs!$B$5) | E4: =E3*(1-Inputs!$B$5) | F4: =F3*(1-Inputs!$B$5) | G4: =G3*(1-Inputs!$B$5)
A5: D&A | C5: =C2*Inputs!$B$6 | D5: =D2*Inputs!$B$6 | E5: =E2*Inputs!$B$6 | F5: =F2*Inputs!$B$6 | G5: =G2*Inputs!$B$6
A6: Capex | C6: =C2*Inputs!$B$7 | D6: =D2*Inputs!$B$7 | E6: =E2*Inputs!$B$7 | F6: =F2*Inputs!$B$7 | G6: =G2*Inputs!$B$7
A7: NWC | B7: =B2*Inputs!$B$8 | C7: =C2*Inputs!$B$8 | D7: =D2*Inputs!$B$8 | E7: =E2*Inputs!$B$8 | F7: =F2*Inputs!$B$8 | G7: =G2*Inputs!$B$8
A8: Change in NWC | C8: =C7-B7 | D8: =D7-C7 | E8: =E7-D7 | F8: =F7-E7 | G8: =G7-F7
A9: FCFF | C9: =C4+C5-C6-C8 | D9: =D4+D5-D6-D8 | E9: =E4+E5-E6-E8 | F9: =F4+F5-F6-F8 | G9: =G4+G5-G6-G8
A10: Discount factor | C10: =(1+Inputs!$B$19)^(-C1) | D10: =(1+Inputs!$B$19)^(-D1) | E10: =(1+Inputs!$B$19)^(-E1) | F10: =(1+Inputs!$B$19)^(-F1) | G10: =(1+Inputs!$B$19)^(-G1)
A11: PV of FCFF | C11: =C9*C10 | D11: =D9*D10 | E11: =E9*E10 | F11: =F9*F10 | G11: =G9*G10
A14: Sum of PV (explicit period) | B14: =SUM(C11:G11)
A15: Terminal value (Gordon) | B15: =G9*(1+Inputs!$B$14)/(Inputs!$B$19-Inputs!$B$14)
A16: PV of terminal value | B16: =B15*(1+Inputs!$B$19)^(-G1)
A17: Enterprise value | B17: =B14+B16
A18: Less: net debt | B18: =Inputs!$B$15
A19: Equity value | B19: =B17-B18
A20: Value per share | B20: =IF(Inputs!$B$16>0,B19/Inputs!$B$16,"n/a")
A21: TV as % of EV | B21: =B16/B17

Sheet Sensitivity
A1: Enterprise value: wacc (rows) x terminal_growth (columns)
A2: Static values computed by the Python model (Excel data tables are not written by openpyxl).
A3: wacc | B3: 0.01 | C3: 0.015 | D3: 0.02 | E3: 0.025 | F3: 0.03
A4: 0.0521 | B4: 2593.2013 | C4: 2894.2602 | D4: 3289.1069 | E4: 3829.6535 | F4: 4614.7913
A5: 0.0621 | B5: 2089.0392 | C5: 2273.5472 | D5: 2501.8814 | E5: 2791.7612 | F5: 3171.9461
A6: 0.0721 | B6: 1747.4469 | C6: 1870.436 | D6: 2017.0315 | E6: 2194.7512 | F6: 2414.6847
A7: 0.0821 | B7: 1500.7727 | C7: 1587.6304 | D7: 1688.4748 | E7: 1806.9802 | F7: 1948.2314
A8: 0.0921 | B8: 1314.326 | C8: 1378.3125 | D8: 1451.1737 | E8: 1534.8935 | F8: 1632.0947
